pywinlayout/__init__.py
pywinlayout/utils.py
pywinlayout-0.1.0.dist-info/METADATA
pywinlayout-0.1.0.dist-info/WHEEL
pywinlayout-0.1.0.dist-info/licenses/LICENSE
pywinlayout-0.1.0.dist-info/RECORD
