Metadata-Version: 2.4
Name: pywinlayout
Version: 0.1.0
Summary: A library for managing window layouts on Windows
Author-email: ZackaryW <36378555+ZackaryW@users.noreply.github.com>
License-File: LICENSE
Requires-Python: >=3.8
Requires-Dist: pygetwindow>=0.0.9
Requires-Dist: pywin32>=308
Requires-Dist: screeninfo>=0.8.1
